openmedicalio/__init__.py
openmedicalio/client.py
openmedicalio-0.0.5.dist-info/LICENSE
openmedicalio-0.0.5.dist-info/METADATA
openmedicalio-0.0.5.dist-info/WHEEL
openmedicalio-0.0.5.dist-info/top_level.txt
openmedicalio-0.0.5.dist-info/RECORD
