Metadata-Version: 2.1
Name: openmedicalio
Version: 0.0.5
Summary: API client for natural language processing tools by Open Medical IO
Home-page: https://github.com/open-medical-io/entities
Author: Open Medical IO
Author-email: info@openmedical.io
License: UNKNOWN
Platform: UNKNOWN
Classifier: Programming Language :: Python :: 3
Classifier: License :: OSI Approved :: MIT License
Classifier: Operating System :: OS Independent
